{
    "version": 1,
    "revision": 0,
    "rules": [
        {
            "primary-output": "C:\\dev\\Turbo\\bin-int\\Debug-x64\\Turbo\\GameSystem.h.obj",
            "outputs": [
                "C:\\dev\\Turbo\\bin-int\\Debug-x64\\Turbo\\vc143.pdb",
                "C:\\dev\\Turbo\\bin-int\\Debug-x64\\Turbo\\",
                "C:\\dev\\Turbo\\bin-int\\Debug-x64\\Turbo\\GameSystem.h.ifc"
            ],
            "provides": [
                {
                    "logical-name": "src\\Engine\\Subsystems\\GameSystem.h",
                    "source-path": "c:\\dev\\turbo\\turbo\\src\\engine\\subsystems\\gamesystem.h",
                    "lookup-method": "absolute"
                }
            ],
            "requires": []
        }
    ]
}